LICENSE
README.md
nautobot_plugin_chatops_grafana/__init__.py
nautobot_plugin_chatops_grafana/api/__init__.py
nautobot_plugin_chatops_grafana/api/urls.py
nautobot_plugin_chatops_grafana/api/views/__init__.py
nautobot_plugin_chatops_grafana/api/views/generic.py
nautobot_plugin_chatops_grafana/diffsync/models.py
nautobot_plugin_chatops_grafana/diffsync/sync.py
nautobot_plugin_chatops_grafana/django1.json
nautobot_plugin_chatops_grafana/exceptions.py
nautobot_plugin_chatops_grafana/filters.py
nautobot_plugin_chatops_grafana/forms.py
nautobot_plugin_chatops_grafana/grafana.py
nautobot_plugin_chatops_grafana/helpers.py
nautobot_plugin_chatops_grafana/management/commands/gen_panels_from_dashboard.py
nautobot_plugin_chatops_grafana/management/commands/import_panels.py
nautobot_plugin_chatops_grafana/management/commands/validate_schema.py
nautobot_plugin_chatops_grafana/migrations/0001_initial.py
nautobot_plugin_chatops_grafana/migrations/__init__.py
nautobot_plugin_chatops_grafana/models.py
nautobot_plugin_chatops_grafana/navigation.py
nautobot_plugin_chatops_grafana/panels.yml
nautobot_plugin_chatops_grafana/schema/schemas/panels.yml
nautobot_plugin_chatops_grafana/static/grafana/grafana_icon.png
nautobot_plugin_chatops_grafana/static/grafana/grafana_icon.svg
nautobot_plugin_chatops_grafana/tables.py
nautobot_plugin_chatops_grafana/templates/nautobot_plugin_chatops_grafana/dashboard_list.html
nautobot_plugin_chatops_grafana/templates/nautobot_plugin_chatops_grafana/panel_list.html
nautobot_plugin_chatops_grafana/templates/nautobot_plugin_chatops_grafana/panels_sync.html
nautobot_plugin_chatops_grafana/templates/nautobot_plugin_chatops_grafana/sync.html
nautobot_plugin_chatops_grafana/templates/nautobot_plugin_chatops_grafana/sync_confirmation.html
nautobot_plugin_chatops_grafana/templates/nautobot_plugin_chatops_grafana/variable_list.html
nautobot_plugin_chatops_grafana/templates/nautobot_plugin_chatops_grafana/variables_sync.html
nautobot_chatops_grafana-1.1.0.dist-info/LICENSE
nautobot_chatops_grafana-1.1.0.dist-info/METADATA
nautobot_chatops_grafana-1.1.0.dist-info/WHEEL
nautobot_chatops_grafana-1.1.0.dist-info/entry_points.txt
nautobot_chatops_grafana-1.1.0.dist-info/RECORD
