Metadata-Version: 2.1
Name: nautobot-chatops-grafana
Version: 1.1.0
Summary: Nautobot Plugin Chatops Grafana
Home-page: https://github.com/nautobot/nautobot-plugin-chatops-grafana
License: Apache-2.0
Keywords: nautobot,nautobot-plugin
Author: Network to Code, LLC
Author-email: opensource@networktocode.com
Requires-Python: >=3.7,<4.0
Classifier: License :: OSI Approved :: Apache Software License
Classifier: Programming Language :: Python :: 3
Classifier: Programming Language :: Python :: 3.7
Classifier: Programming Language :: Python :: 3.8
Classifier: Programming Language :: Python :: 3.9
Classifier: Programming Language :: Python :: 3.10
Classifier: Programming Language :: Python :: 3.11
Provides-Extra: nautobot
Requires-Dist: diffsync (>=1.3.0,<2.0.0)
Requires-Dist: isodate (>=0.6.0,<0.7.0)
Requires-Dist: nautobot (>=1.0.0,<2.0.0) ; extra == "nautobot"
Requires-Dist: nautobot-chatops (>=1.3.1,<2.0.0)
Requires-Dist: pydantic (>=1.8.2,<2.0.0)
Requires-Dist: schema-enforcer (>=1.1.2,<2.0.0)
Project-URL: Repository, https://github.com/nautobot/nautobot-plugin-chatops-grafana
